PyTado/__init__.py
PyTado/__main__.py
PyTado/const.py
PyTado/interface.py
PyTado/zone.py
jorgenvatle_python_tado-0.13.7.dist-info/AUTHORS
jorgenvatle_python_tado-0.13.7.dist-info/LICENSE
jorgenvatle_python_tado-0.13.7.dist-info/METADATA
jorgenvatle_python_tado-0.13.7.dist-info/WHEEL
jorgenvatle_python_tado-0.13.7.dist-info/entry_points.txt
jorgenvatle_python_tado-0.13.7.dist-info/top_level.txt
jorgenvatle_python_tado-0.13.7.dist-info/RECORD
