Metadata-Version: 2.1
Name: jorgenvatle-python-tado
Version: 0.13.7
Summary: PyTado from chrism0dwk, modfied by w.malgadey, diplix, michaelarnauts, LenhartStephan, splifter, syssi, andersonshatch, Yippy, p0thi
Home-page: https://github.com/palazzem/PyTado
Author: chrism0dwk, w.malgadey
Author-email: chrism0dwk@gmail.com, w.malgadey@gmail.com
License: GPL3
Keywords: tado
Platform: any
Classifier: Development Status :: 3 - Alpha
Classifier: Topic :: Home Automation
Classifier: Intended Audience :: Developers
Classifier: License :: OSI Approved :: GNU General Public License v3 (GPLv3)
Classifier: Natural Language :: English
Classifier: Programming Language :: Python :: 3
Classifier: Programming Language :: Python :: 3.3
Classifier: Programming Language :: Python :: 3.5
License-File: LICENSE
License-File: AUTHORS
Requires-Dist: requests
